lesting.api.client-0.1.1-py3.9-nspkg.pth
lesting/api/client/__init__.py
lesting/api/client/discovery.py
lesting/api/client/resources.py
lesting/api/client/schemas.py
lesting.api.client-0.1.1.dist-info/LICENSE
lesting.api.client-0.1.1.dist-info/METADATA
lesting.api.client-0.1.1.dist-info/WHEEL
lesting.api.client-0.1.1.dist-info/namespace_packages.txt
lesting.api.client-0.1.1.dist-info/top_level.txt
lesting.api.client-0.1.1.dist-info/RECORD
